{
  "applications": ["library"],
  "changelogDate": "20230912213309",
  "dto": "no",
  "embedded": false,
  "entityTableName": "borrowed_book",
  "fields": [
    {
      "fieldName": "borrowDate",
      "fieldType": "LocalDate"
    }
  ],
  "fluentMethods": true,
  "jpaMetamodelFiltering": true,
  "name": "BorrowedBook",
  "pagination": "pagination",
  "readOnly": false,
  "relationships": [
    {
      "otherEntityField": "name",
      "otherEntityName": "book",
      "ownerSide": true,
      "relationshipName": "book",
      "relationshipSide": "left",
      "relationshipType": "one-to-one"
    },
    {
      "otherEntityField": "email",
      "otherEntityName": "client",
      "ownerSide": true,
      "relationshipName": "client",
      "relationshipSide": "left",
      "relationshipType": "one-to-one"
    }
  ],
  "service": "serviceImpl"
}
